pyseto/__init__.py
pyseto/exceptions.py
pyseto/key.py
pyseto/key_interface.py
pyseto/key_nist.py
pyseto/key_sodium.py
pyseto/paseto.py
pyseto/py.typed
pyseto/pyseto.py
pyseto/token.py
pyseto/utils.py
pyseto/versions/__init__.py
pyseto/versions/v1.py
pyseto/versions/v2.py
pyseto/versions/v3.py
pyseto/versions/v4.py
pyseto-1.9.1.dist-info/licenses/LICENSE
pyseto-1.9.1.dist-info/WHEEL
pyseto-1.9.1.dist-info/METADATA
pyseto-1.9.1.dist-info/RECORD
