Metadata-Version: 2.4
Name: pyseto
Version: 1.9.1
Summary: A Python implementation of PASETO/PASERK.
Author: Ajitomi Daisuke
Author-email: Ajitomi Daisuke <dajiaji@gmail.com>
License-Expression: MIT
License-File: LICENSE
Classifier: License :: OSI Approved :: MIT License
Classifier: Programming Language :: Python
Classifier: Programming Language :: Python :: 3
Classifier: Programming Language :: Python :: 3 :: Only
Classifier: Programming Language :: Python :: 3.10
Classifier: Programming Language :: Python :: 3.11
Classifier: Programming Language :: Python :: 3.12
Classifier: Programming Language :: Python :: 3.13
Classifier: Programming Language :: Python :: 3.14
Classifier: Typing :: Typed
Requires-Dist: argon2-cffi>=23.1.0
Requires-Dist: cryptography>=42.0.1,<47
Requires-Dist: iso8601>=1.0.2,<3.0.0
Requires-Dist: pycryptodomex>=3.18.0
Requires-Python: >=3.10, <4.0
Project-URL: Repository, https://github.com/dajiaji/pyseto
